{
  "location": {
    "name": "Castellone",
    "region": "Molise",
    "country": "Italy",
    "lat": 41.5,
    "lon": 14.45,
    "tz_id": "Europe/Rome",
    "localtime_epoch": 1743000111,
    "localtime": "2025-03-26 15:41"
  },
  "current": {
    "last_updated_epoch": 1742999400,
    "last_updated": "2025-03-26 15:30",
    "temp_c": 8.7,
    "temp_f": 47.7,
    "is_day": 1,
    "condition": {
      "text": "Lluvia  moderada a intervalos",
      "icon": "//cdn.weatherapi.com/weather/64x64/day/176.png",
      "code": 1063
    },
    "wind_mph": 4.9,
    "wind_kph": 7.9,
    "wind_degree": 12,
    "wind_dir": "NNE",
    "pressure_mb": 1011,
    "pressure_in": 29.85,
    "precip_mm": 0.11,
    "precip_in": 0,
    "humidity": 89,
    "cloud": 100,
    "feelslike_c": 7.5,
    "feelslike_f": 45.5,
    "windchill_c": 7.5,
    "windchill_f": 45.5,
    "heatindex_c": 8.7,
    "heatindex_f": 47.7,
    "dewpoint_c": 7,
    "dewpoint_f": 44.6,
    "vis_km": 10,
    "vis_miles": 6,
    "uv": 0.9,
    "gust_mph": 6.3,
    "gust_kph": 10.1
  },
  "forecast": {
    "forecastday": [
      {
        "date": "2025-03-26",
        "date_epoch": 1742947200,
        "day": {
          "maxtemp_c": 8.9,
          "maxtemp_f": 48.1,
          "mintemp_c": 5.6,
          "mintemp_f": 42,
          "avgtemp_c": 8,
          "avgtemp_f": 46.4,
          "maxwind_mph": 5.8,
          "maxwind_kph": 9.4,
          "totalprecip_mm": 1.81,
          "totalprecip_in": 0.07,
          "totalsnow_cm": 0,
          "avgvis_km": 9,
          "avgvis_miles": 5,
          "avghumidity": 91,
          "daily_will_it_rain": 1,
          "daily_chance_of_rain": 86,
          "daily_will_it_snow": 0,
          "daily_chance_of_snow": 0,
          "condition": {
            "text": "Lluvia  moderada a intervalos",
            "icon": "//cdn.weatherapi.com/weather/64x64/day/176.png",
            "code": 1063
          },
          "uv": 0.4
        },
        "astro": {
          "sunrise": "05:55 AM",
          "sunset": "06:20 PM",
          "moonrise": "04:28 AM",
          "moonset": "02:47 PM",
          "moon_phase": "Waning Crescent",
          "moon_illumination": 16,
          "is_moon_up": 0,
          "is_sun_up": 0
        },
        "hour": [
          {
            "time_epoch": 1742943600,
            "time": "2025-03-26 00:00",
            "temp_c": 8,
            "temp_f": 46.5,
            "is_day": 0,
            "condition": {
              "text": "Parcialmente nublado",
              "icon": "//cdn.weatherapi.com/weather/64x64/night/116.png",
              "code": 1003
            },
            "wind_mph": 3.8,
            "wind_kph": 6.1,
            "wind_degree": 333,
            "wind_dir": "NNW",
            "pressure_mb": 1015,
            "pressure_in": 29.99,
            "precip_mm": 0,
            "precip_in": 0,
            "snow_cm": 0,
            "humidity": 83,
            "cloud": 48,
            "feelslike_c": 7.2,
            "feelslike_f": 44.9,
            "windchill_c": 7.2,
            "windchill_f": 44.9,
            "heatindex_c": 8,
            "heatindex_f": 46.5,
            "dewpoint_c": 5.4,
            "dewpoint_f": 41.7,
            "will_it_rain": 0,
            "chance_of_rain": 0,
            "will_it_snow": 0,
            "chance_of_snow": 0,
            "vis_km": 10,
            "vis_miles": 6,
            "gust_mph": 7,
            "gust_kph": 11.3,
            "uv": 0
          },
          {
            "time_epoch": 1742947200,
            "time": "2025-03-26 01:00",
            "temp_c": 8.5,
            "temp_f": 47.3,
            "is_day": 0,
            "condition": {
              "text": "Lluvia  moderada a intervalos",
              "icon": "//cdn.weatherapi.com/weather/64x64/night/176.png",
              "code": 1063
            },
            "wind_mph": 4,
            "wind_kph": 6.5,
            "wind_degree": 340,
            "wind_dir": "NNW",
            "pressure_mb": 1015,
            "pressure_in": 29.97,
            "precip_mm": 0.03,
            "precip_in": 0,
            "snow_cm": 0,
            "humidity": 82,
            "cloud": 100,
            "feelslike_c": 7.6,
            "feelslike_f": 45.7,
            "windchill_c": 7.6,
            "windchill_f": 45.7,
            "heatindex_c": 8.5,
            "heatindex_f": 47.3,
            "dewpoint_c": 5.6,
            "dewpoint_f": 42.2,
            "will_it_rain": 0,
            "chance_of_rain": 70,
            "will_it_snow": 0,
            "chance_of_snow": 0,
            "vis_km": 10,
            "vis_miles": 6,
            "gust_mph": 6.8,
            "gust_kph": 10.9,
            "uv": 0
          },
          {
            "time_epoch": 1742950800,
            "time": "2025-03-26 02:00",
            "temp_c": 8.4,
            "temp_f": 47.1,
            "is_day": 0,
            "condition": {
              "text": "Lluvia  moderada a intervalos",
              "icon": "//cdn.weatherapi.com/weather/64x64/night/176.png",
              "code": 1063
            },
            "wind_mph": 4,
            "wind_kph": 6.5,
            "wind_degree": 350,
            "wind_dir": "N",
            "pressure_mb": 1014,
            "pressure_in": 29.95,
            "precip_mm": 0.04,
            "precip_in": 0,
            "snow_cm": 0,
            "humidity": 84,
            "cloud": 96,
            "feelslike_c": 7.5,
            "feelslike_f": 45.4,
            "windchill_c": 7.5,
            "windchill_f": 45.4,
            "heatindex_c": 8.4,
            "heatindex_f": 47.1,
            "dewpoint_c": 5.8,
            "dewpoint_f": 42.5,
            "will_it_rain": 1,
            "chance_of_rain": 86,
            "will_it_snow": 0,
            "chance_of_snow": 0,
            "vis_km": 10,
            "vis_miles": 6,
            "gust_mph": 6.7,
            "gust_kph": 10.8,
            "uv": 0
          },
          {
            "time_epoch": 1742954400,
            "time": "2025-03-26 03:00",
            "temp_c": 8.2,
            "temp_f": 46.8,
            "is_day": 0,
            "condition": {
              "text": "Lluvia  moderada a intervalos",
              "icon": "//cdn.weatherapi.com/weather/64x64/night/176.png",
              "code": 1063
            },
            "wind_mph": 3.8,
            "wind_kph": 6.1,
            "wind_degree": 340,
            "wind_dir": "NNW",
            "pressure_mb": 1014,
            "pressure_in": 29.94,
            "precip_mm": 0.08,
            "precip_in": 0,
            "snow_cm": 0,
            "humidity": 87,
            "cloud": 99,
            "feelslike_c": 7.4,
            "feelslike_f": 45.3,
            "windchill_c": 7.4,
            "windchill_f": 45.3,
            "heatindex_c": 8.2,
            "heatindex_f": 46.8,
            "dewpoint_c": 6.2,
            "dewpoint_f": 43.1,
            "will_it_rain": 1,
            "chance_of_rain": 100,
            "will_it_snow": 0,
            "chance_of_snow": 0,
            "vis_km": 10,
            "vis_miles": 6,
            "gust_mph": 6.3,
            "gust_kph": 10.2,
            "uv": 0
          },
          {
            "time_epoch": 1742958000,
            "time": "2025-03-26 04:00",
            "temp_c": 8.1,
            "temp_f": 46.6,
            "is_day": 0,
            "condition": {
              "text": "Lluvia  moderada a intervalos",
              "icon": "//cdn.weatherapi.com/weather/64x64/night/176.png",
              "code": 1063
            },
            "wind_mph": 2.7,
            "wind_kph": 4.3,
            "wind_degree": 335,
            "wind_dir": "NNW",
            "pressure_mb": 1013,
            "pressure_in": 29.92,
            "precip_mm": 0.09,
            "precip_in": 0,
            "snow_cm": 0,
            "humidity": 90,
            "cloud": 70,
            "feelslike_c": 7.9,
            "feelslike_f": 46.1,
            "windchill_c": 7.9,
            "windchill_f": 46.1,
            "heatindex_c": 8.1,
            "heatindex_f": 46.6,
            "dewpoint_c": 6.6,
            "dewpoint_f": 43.9,
            "will_it_rain": 1,
            "chance_of_rain": 100,
            "will_it_snow": 0,
            "chance_of_snow": 0,
            "vis_km": 10,
            "vis_miles": 6,
            "gust_mph": 4.5,
            "gust_kph": 7.2,
            "uv": 0
          },
          {
            "time_epoch": 1742961600,
            "time": "2025-03-26 05:00",
            "temp_c": 8,
            "temp_f": 46.5,
            "is_day": 0,
            "condition": {
              "text": "Lluvia  moderada a intervalos",
              "icon": "//cdn.weatherapi.com/weather/64x64/night/176.png",
              "code": 1063
            },
            "wind_mph": 3.4,
            "wind_kph": 5.4,
            "wind_degree": 359,
            "wind_dir": "N",
            "pressure_mb": 1013,
            "pressure_in": 29.91,
            "precip_mm": 0.04,
            "precip_in": 0,
            "snow_cm": 0,
            "humidity": 91,
            "cloud": 72,
            "feelslike_c": 7.4,
            "feelslike_f": 45.3,
            "windchill_c": 7.4,
            "windchill_f": 45.3,
            "heatindex_c": 8,
            "heatindex_f": 46.5,
            "dewpoint_c": 6.7,
            "dewpoint_f": 44.1,
            "will_it_rain": 1,
            "chance_of_rain": 74,
            "will_it_snow": 0,
            "chance_of_snow": 0,
            "vis_km": 10,
            "vis_miles": 6,
            "gust_mph": 5.7,
            "gust_kph": 9.1,
            "uv": 0
          },
          {
            "time_epoch": 1742965200,
            "time": "2025-03-26 06:00",
            "temp_c": 7.9,
            "temp_f": 46.2,
            "is_day": 1,
            "condition": {
              "text": "Neblina",
              "icon": "//cdn.weatherapi.com/weather/64x64/day/143.png",
              "code": 1030
            },
            "wind_mph": 4,
            "wind_kph": 6.5,
            "wind_degree": 13,
            "wind_dir": "NNE",
            "pressure_mb": 1012,
            "pressure_in": 29.9,
            "precip_mm": 0.01,
            "precip_in": 0,
            "snow_cm": 0,
            "humidity": 94,
            "cloud": 82,
            "feelslike_c": 6.9,
            "feelslike_f": 44.5,
            "windchill_c": 6.9,
            "windchill_f": 44.5,
            "heatindex_c": 7.9,
            "heatindex_f": 46.2,
            "dewpoint_c": 7,
            "dewpoint_f": 44.7,
            "will_it_rain": 1,
            "chance_of_rain": 83,
            "will_it_snow": 0,
            "chance_of_snow": 0,
            "vis_km": 2,
            "vis_miles": 1,
            "gust_mph": 6.7,
            "gust_kph": 10.8,
            "uv": 0
          },
          {
            "time_epoch": 1742968800,
            "time": "2025-03-26 07:00",
            "temp_c": 8.3,
            "temp_f": 47,
            "is_day": 1,
            "condition": {
              "text": "Neblina",
              "icon": "//cdn.weatherapi.com/weather/64x64/day/143.png",
              "code": 1030
            },
            "wind_mph": 3.8,
            "wind_kph": 6.1,
            "wind_degree": 17,
            "wind_dir": "NNE",
            "pressure_mb": 1012,
            "pressure_in": 29.9,
            "precip_mm": 0.01,
            "precip_in": 0,
            "snow_cm": 0,
            "humidity": 95,
            "cloud": 100,
            "feelslike_c": 7.5,
            "feelslike_f": 45.5,
            "windchill_c": 7.5,
            "windchill_f": 45.5,
            "heatindex_c": 8.3,
            "heatindex_f": 47,
            "dewpoint_c": 7.6,
            "dewpoint_f": 45.6,
            "will_it_rain": 0,
            "chance_of_rain": 66,
            "will_it_snow": 0,
            "chance_of_snow": 0,
            "vis_km": 2,
            "vis_miles": 1,
            "gust_mph": 5.7,
            "gust_kph": 9.1,
            "uv": 0.1
          },
          {
            "time_epoch": 1742972400,
            "time": "2025-03-26 08:00",
            "temp_c": 8.8,
            "temp_f": 47.9,
            "is_day": 1,
            "condition": {
              "text": "Neblina",
              "icon": "//cdn.weatherapi.com/weather/64x64/day/143.png",
              "code": 1030
            },
            "wind_mph": 4.9,
            "wind_kph": 7.9,
            "wind_degree": 10,
            "wind_dir": "N",
            "pressure_mb": 1012,
            "pressure_in": 29.88,
            "precip_mm": 0.09,
            "precip_in": 0,
            "snow_cm": 0,
            "humidity": 94,
            "cloud": 100,
            "feelslike_c": 7.6,
            "feelslike_f": 45.8,
            "windchill_c": 7.6,
            "windchill_f": 45.8,
            "heatindex_c": 8.8,
            "heatindex_f": 47.9,
            "dewpoint_c": 7.9,
            "dewpoint_f": 46.3,
            "will_it_rain": 1,
            "chance_of_rain": 100,
            "will_it_snow": 0,
            "chance_of_snow": 0,
            "vis_km": 2,
            "vis_miles": 1,
            "gust_mph": 6.8,
            "gust_kph": 10.9,
            "uv": 0.2
          },
          {
            "time_epoch": 1742976000,
            "time": "2025-03-26 09:00",
            "temp_c": 8.8,
            "temp_f": 47.9,
            "is_day": 1,
            "condition": {
              "text": "Ligeras precipitaciones",
              "icon": "//cdn.weatherapi.com/weather/64x64/day/353.png",
              "code": 1240
            },
            "wind_mph": 4.7,
            "wind_kph": 7.6,
            "wind_degree": 10,
            "wind_dir": "N",
            "pressure_mb": 1012,
            "pressure_in": 29.89,
            "precip_mm": 0.36,
            "precip_in": 0.01,
            "snow_cm": 0,
            "humidity": 94,
            "cloud": 100,
            "feelslike_c": 7.7,
            "feelslike_f": 45.9,
            "windchill_c": 7.7,
            "windchill_f": 45.9,
            "heatindex_c": 8.8,
            "heatindex_f": 47.9,
            "dewpoint_c": 8,
            "dewpoint_f": 46.3,
            "will_it_rain": 1,
            "chance_of_rain": 100,
            "will_it_snow": 0,
            "chance_of_snow": 0,
            "vis_km": 10,
            "vis_miles": 6,
            "gust_mph": 6.5,
            "gust_kph": 10.5,
            "uv": 0.6
          },
          {
            "time_epoch": 1742979600,
            "time": "2025-03-26 10:00",
            "temp_c": 8.7,
            "temp_f": 47.7,
            "is_day": 1,
            "condition": {
              "text": "Ligeras precipitaciones",
              "icon": "//cdn.weatherapi.com/weather/64x64/day/353.png",
              "code": 1240
            },
            "wind_mph": 5.1,
            "wind_kph": 8.3,
            "wind_degree": 2,
            "wind_dir": "N",
            "pressure_mb": 1012,
            "pressure_in": 29.89,
            "precip_mm": 0.26,
            "precip_in": 0.01,
            "snow_cm": 0,
            "humidity": 96,
            "cloud": 100,
            "feelslike_c": 7.4,
            "feelslike_f": 45.4,
            "windchill_c": 7.4,
            "windchill_f": 45.4,
            "heatindex_c": 8.7,
            "heatindex_f": 47.7,
            "dewpoint_c": 8,
            "dewpoint_f": 46.5,
            "will_it_rain": 1,
            "chance_of_rain": 100,
            "will_it_snow": 0,
            "chance_of_snow": 0,
            "vis_km": 10,
            "vis_miles": 6,
            "gust_mph": 7.2,
            "gust_kph": 11.5,
            "uv": 1.2
          },
          {
            "time_epoch": 1742983200,
            "time": "2025-03-26 11:00",
            "temp_c": 8.6,
            "temp_f": 47.5,
            "is_day": 1,
            "condition": {
              "text": "Ligeras precipitaciones",
              "icon": "//cdn.weatherapi.com/weather/64x64/day/353.png",
              "code": 1240
            },
            "wind_mph": 5.4,
            "wind_kph": 8.6,
            "wind_degree": 0,
            "wind_dir": "N",
            "pressure_mb": 1012,
            "pressure_in": 29.89,
            "precip_mm": 0.24,
            "precip_in": 0.01,
            "snow_cm": 0,
            "humidity": 94,
            "cloud": 100,
            "feelslike_c": 7.2,
            "feelslike_f": 45,
            "windchill_c": 7.2,
            "windchill_f": 45,
            "heatindex_c": 8.6,
            "heatindex_f": 47.5,
            "dewpoint_c": 7.7,
            "dewpoint_f": 45.9,
            "will_it_rain": 1,
            "chance_of_rain": 100,
            "will_it_snow": 0,
            "chance_of_snow": 0,
            "vis_km": 10,
            "vis_miles": 6,
            "gust_mph": 7.5,
            "gust_kph": 12.1,
            "uv": 1.5
          },
          {
            "time_epoch": 1742986800,
            "time": "2025-03-26 12:00",
            "temp_c": 8.4,
            "temp_f": 47.1,
            "is_day": 1,
            "condition": {
              "text": "Ligeras precipitaciones",
              "icon": "//cdn.weatherapi.com/weather/64x64/day/353.png",
              "code": 1240
            },
            "wind_mph": 5.6,
            "wind_kph": 9,
            "wind_degree": 12,
            "wind_dir": "NNE",
            "pressure_mb": 1012,
            "pressure_in": 29.88,
            "precip_mm": 0.22,
            "precip_in": 0.01,
            "snow_cm": 0,
            "humidity": 94,
            "cloud": 100,
            "feelslike_c": 6.9,
            "feelslike_f": 44.5,
            "windchill_c": 6.9,
            "windchill_f": 44.5,
            "heatindex_c": 8.4,
            "heatindex_f": 47.1,
            "dewpoint_c": 7.5,
            "dewpoint_f": 45.5,
            "will_it_rain": 1,
            "chance_of_rain": 100,
            "will_it_snow": 0,
            "chance_of_snow": 0,
            "vis_km": 10,
            "vis_miles": 6,
            "gust_mph": 7.8,
            "gust_kph": 12.5,
            "uv": 1.1
          },
          {
            "time_epoch": 1742990400,
            "time": "2025-03-26 13:00",
            "temp_c": 8.3,
            "temp_f": 47,
            "is_day": 1,
            "condition": {
              "text": "Lluvia  moderada a intervalos",
              "icon": "//cdn.weatherapi.com/weather/64x64/day/176.png",
              "code": 1063
            },
            "wind_mph": 5.8,
            "wind_kph": 9.4,
            "wind_degree": 8,
            "wind_dir": "N",
            "pressure_mb": 1012,
            "pressure_in": 29.88,
            "precip_mm": 0.11,
            "precip_in": 0,
            "snow_cm": 0,
            "humidity": 92,
            "cloud": 100,
            "feelslike_c": 6.8,
            "feelslike_f": 44.2,
            "windchill_c": 6.8,
            "windchill_f": 44.2,
            "heatindex_c": 8.4,
            "heatindex_f": 47,
            "dewpoint_c": 7.1,
            "dewpoint_f": 44.8,
            "will_it_rain": 1,
            "chance_of_rain": 100,
            "will_it_snow": 0,
            "chance_of_snow": 0,
            "vis_km": 10,
            "vis_miles": 6,
            "gust_mph": 8,
            "gust_kph": 12.9,
            "uv": 1
          },
          {
            "time_epoch": 1742994000,
            "time": "2025-03-26 14:00",
            "temp_c": 8.7,
            "temp_f": 47.6,
            "is_day": 1,
            "condition": {
              "text": "Lluvia  moderada a intervalos",
              "icon": "//cdn.weatherapi.com/weather/64x64/day/176.png",
              "code": 1063
            },
            "wind_mph": 5.4,
            "wind_kph": 8.6,
            "wind_degree": 5,
            "wind_dir": "N",
            "pressure_mb": 1011,
            "pressure_in": 29.86,
            "precip_mm": 0.04,
            "precip_in": 0,
            "snow_cm": 0,
            "humidity": 91,
            "cloud": 99,
            "feelslike_c": 7.3,
            "feelslike_f": 45.2,
            "windchill_c": 7.3,
            "windchill_f": 45.2,
            "heatindex_c": 8.7,
            "heatindex_f": 47.6,
            "dewpoint_c": 7.2,
            "dewpoint_f": 45,
            "will_it_rain": 1,
            "chance_of_rain": 72,
            "will_it_snow": 0,
            "chance_of_snow": 0,
            "vis_km": 10,
            "vis_miles": 6,
            "gust_mph": 6.9,
            "gust_kph": 11.1,
            "uv": 1.3
          },
          {
            "time_epoch": 1742997600,
            "time": "2025-03-26 15:00",
            "temp_c": 8.7,
            "temp_f": 47.7,
            "is_day": 1,
            "condition": {
              "text": "Lluvia  moderada a intervalos",
              "icon": "//cdn.weatherapi.com/weather/64x64/day/176.png",
              "code": 1063
            },
            "wind_mph": 4.9,
            "wind_kph": 7.9,
            "wind_degree": 12,
            "wind_dir": "NNE",
            "pressure_mb": 1011,
            "pressure_in": 29.85,
            "precip_mm": 0.11,
            "precip_in": 0,
            "snow_cm": 0,
            "humidity": 89,
            "cloud": 100,
            "feelslike_c": 7.5,
            "feelslike_f": 45.5,
            "windchill_c": 7.5,
            "windchill_f": 45.5,
            "heatindex_c": 8.7,
            "heatindex_f": 47.7,
            "dewpoint_c": 7,
            "dewpoint_f": 44.6,
            "will_it_rain": 1,
            "chance_of_rain": 100,
            "will_it_snow": 0,
            "chance_of_snow": 0,
            "vis_km": 10,
            "vis_miles": 6,
            "gust_mph": 6.3,
            "gust_kph": 10.1,
            "uv": 0.9
          },
          {
            "time_epoch": 1743001200,
            "time": "2025-03-26 16:00",
            "temp_c": 8.6,
            "temp_f": 47.4,
            "is_day": 1,
            "condition": {
              "text": "Lluvia  moderada a intervalos",
              "icon": "//cdn.weatherapi.com/weather/64x64/day/176.png",
              "code": 1063
            },
            "wind_mph": 5.6,
            "wind_kph": 9,
            "wind_degree": 9,
            "wind_dir": "N",
            "pressure_mb": 1010,
            "pressure_in": 29.83,
            "precip_mm": 0.05,
            "precip_in": 0,
            "snow_cm": 0,
            "humidity": 88,
            "cloud": 90,
            "feelslike_c": 7.1,
            "feelslike_f": 44.8,
            "windchill_c": 7.1,
            "windchill_f": 44.8,
            "heatindex_c": 8.6,
            "heatindex_f": 47.4,
            "dewpoint_c": 6.7,
            "dewpoint_f": 44.1,
            "will_it_rain": 1,
            "chance_of_rain": 100,
            "will_it_snow": 0,
            "chance_of_snow": 0,
            "vis_km": 10,
            "vis_miles": 6,
            "gust_mph": 7.3,
            "gust_kph": 11.8,
            "uv": 0.6
          },
          {
            "time_epoch": 1743004800,
            "time": "2025-03-26 17:00",
            "temp_c": 8.9,
            "temp_f": 48.1,
            "is_day": 1,
            "condition": {
              "text": "Lluvia  moderada a intervalos",
              "icon": "//cdn.weatherapi.com/weather/64x64/day/176.png",
              "code": 1063
            },
            "wind_mph": 5.4,
            "wind_kph": 8.6,
            "wind_degree": 13,
            "wind_dir": "NNE",
            "pressure_mb": 1010,
            "pressure_in": 29.82,
            "precip_mm": 0.02,
            "precip_in": 0,
            "snow_cm": 0,
            "humidity": 85,
            "cloud": 93,
            "feelslike_c": 7.6,
            "feelslike_f": 45.8,
            "windchill_c": 7.6,
            "windchill_f": 45.8,
            "heatindex_c": 9,
            "heatindex_f": 48.1,
            "dewpoint_c": 6.6,
            "dewpoint_f": 43.8,
            "will_it_rain": 1,
            "chance_of_rain": 71,
            "will_it_snow": 0,
            "chance_of_snow": 0,
            "vis_km": 10,
            "vis_miles": 6,
            "gust_mph": 6.8,
            "gust_kph": 10.9,
            "uv": 0.2
          },
          {
            "time_epoch": 1743008400,
            "time": "2025-03-26 18:00",
            "temp_c": 8.1,
            "temp_f": 46.6,
            "is_day": 1,
            "condition": {
              "text": "Lluvia  moderada a intervalos",
              "icon": "//cdn.weatherapi.com/weather/64x64/day/176.png",
              "code": 1063
            },
            "wind_mph": 3.8,
            "wind_kph": 6.1,
            "wind_degree": 5,
            "wind_dir": "N",
            "pressure_mb": 1010,
            "pressure_in": 29.82,
            "precip_mm": 0.01,
            "precip_in": 0,
            "snow_cm": 0,
            "humidity": 90,
            "cloud": 91,
            "feelslike_c": 7.3,
            "feelslike_f": 45.1,
            "windchill_c": 7.3,
            "windchill_f": 45.1,
            "heatindex_c": 8.1,
            "heatindex_f": 46.6,
            "dewpoint_c": 6.6,
            "dewpoint_f": 43.8,
            "will_it_rain": 0,
            "chance_of_rain": 69,
            "will_it_snow": 0,
            "chance_of_snow": 0,
            "vis_km": 10,
            "vis_miles": 6,
            "gust_mph": 5.4,
            "gust_kph": 8.7,
            "uv": 0
          },
          {
            "time_epoch": 1743012000,
            "time": "2025-03-26 19:00",
            "temp_c": 7.3,
            "temp_f": 45.2,
            "is_day": 0,
            "condition": {
              "text": "Parcialmente nublado",
              "icon": "//cdn.weatherapi.com/weather/64x64/night/116.png",
              "code": 1003
            },
            "wind_mph": 2.9,
            "wind_kph": 4.7,
            "wind_degree": 352,
            "wind_dir": "N",
            "pressure_mb": 1010,
            "pressure_in": 29.82,
            "precip_mm": 0,
            "precip_in": 0,
            "snow_cm": 0,
            "humidity": 93,
            "cloud": 62,
            "feelslike_c": 6.9,
            "feelslike_f": 44.3,
            "windchill_c": 6.9,
            "windchill_f": 44.3,
            "heatindex_c": 7.3,
            "heatindex_f": 45.2,
            "dewpoint_c": 6.2,
            "dewpoint_f": 43.2,
            "will_it_rain": 0,
            "chance_of_rain": 0,
            "will_it_snow": 0,
            "chance_of_snow": 0,
            "vis_km": 10,
            "vis_miles": 6,
            "gust_mph": 4.6,
            "gust_kph": 7.3,
            "uv": 0
          },
          {
            "time_epoch": 1743015600,
            "time": "2025-03-26 20:00",
            "temp_c": 6.9,
            "temp_f": 44.4,
            "is_day": 0,
            "condition": {
              "text": "Parcialmente nublado",
              "icon": "//cdn.weatherapi.com/weather/64x64/night/116.png",
              "code": 1003
            },
            "wind_mph": 1.3,
            "wind_kph": 2.2,
            "wind_degree": 349,
            "wind_dir": "N",
            "pressure_mb": 1010,
            "pressure_in": 29.83,
            "precip_mm": 0,
            "precip_in": 0,
            "snow_cm": 0,
            "humidity": 93,
            "cloud": 44,
            "feelslike_c": 6.9,
            "feelslike_f": 44.4,
            "windchill_c": 6.9,
            "windchill_f": 44.4,
            "heatindex_c": 6.9,
            "heatindex_f": 44.4,
            "dewpoint_c": 5.9,
            "dewpoint_f": 42.6,
            "will_it_rain": 0,
            "chance_of_rain": 0,
            "will_it_snow": 0,
            "chance_of_snow": 0,
            "vis_km": 10,
            "vis_miles": 6,
            "gust_mph": 2.3,
            "gust_kph": 3.6,
            "uv": 0
          },
          {
            "time_epoch": 1743019200,
            "time": "2025-03-26 21:00",
            "temp_c": 6.4,
            "temp_f": 43.6,
            "is_day": 0,
            "condition": {
              "text": "Parcialmente nublado",
              "icon": "//cdn.weatherapi.com/weather/64x64/night/116.png",
              "code": 1003
            },
            "wind_mph": 2.9,
            "wind_kph": 4.7,
            "wind_degree": 343,
            "wind_dir": "NNW",
            "pressure_mb": 1010,
            "pressure_in": 29.83,
            "precip_mm": 0,
            "precip_in": 0,
            "snow_cm": 0,
            "humidity": 93,
            "cloud": 46,
            "feelslike_c": 5.8,
            "feelslike_f": 42.5,
            "windchill_c": 5.8,
            "windchill_f": 42.5,
            "heatindex_c": 6.4,
            "heatindex_f": 43.6,
            "dewpoint_c": 5.5,
            "dewpoint_f": 41.8,
            "will_it_rain": 0,
            "chance_of_rain": 0,
            "will_it_snow": 0,
            "chance_of_snow": 0,
            "vis_km": 10,
            "vis_miles": 6,
            "gust_mph": 5.2,
            "gust_kph": 8.3,
            "uv": 0
          },
          {
            "time_epoch": 1743022800,
            "time": "2025-03-26 22:00",
            "temp_c": 6,
            "temp_f": 42.9,
            "is_day": 0,
            "condition": {
              "text": "Parcialmente nublado",
              "icon": "//cdn.weatherapi.com/weather/64x64/night/116.png",
              "code": 1003
            },
            "wind_mph": 3.6,
            "wind_kph": 5.8,
            "wind_degree": 328,
            "wind_dir": "NNW",
            "pressure_mb": 1010,
            "pressure_in": 29.81,
            "precip_mm": 0,
            "precip_in": 0,
            "snow_cm": 0,
            "humidity": 93,
            "cloud": 43,
            "feelslike_c": 5,
            "feelslike_f": 41,
            "windchill_c": 5,
            "windchill_f": 41,
            "heatindex_c": 6.1,
            "heatindex_f": 42.9,
            "dewpoint_c": 5.1,
            "dewpoint_f": 41.1,
            "will_it_rain": 0,
            "chance_of_rain": 0,
            "will_it_snow": 0,
            "chance_of_snow": 0,
            "vis_km": 10,
            "vis_miles": 6,
            "gust_mph": 6.6,
            "gust_kph": 10.6,
            "uv": 0
          },
          {
            "time_epoch": 1743026400,
            "time": "2025-03-26 23:00",
            "temp_c": 5.6,
            "temp_f": 42,
            "is_day": 0,
            "condition": {
              "text": "Parcialmente nublado",
              "icon": "//cdn.weatherapi.com/weather/64x64/night/116.png",
              "code": 1003
            },
            "wind_mph": 3.8,
            "wind_kph": 6.1,
            "wind_degree": 321,
            "wind_dir": "NW",
            "pressure_mb": 1009,
            "pressure_in": 29.8,
            "precip_mm": 0,
            "precip_in": 0,
            "snow_cm": 0,
            "humidity": 94,
            "cloud": 39,
            "feelslike_c": 4.4,
            "feelslike_f": 39.8,
            "windchill_c": 4.4,
            "windchill_f": 39.8,
            "heatindex_c": 5.6,
            "heatindex_f": 42,
            "dewpoint_c": 4.6,
            "dewpoint_f": 40.3,
            "will_it_rain": 0,
            "chance_of_rain": 0,
            "will_it_snow": 0,
            "chance_of_snow": 0,
            "vis_km": 10,
            "vis_miles": 6,
            "gust_mph": 7.3,
            "gust_kph": 11.8,
            "uv": 0
          }
        ]
      },
      {
        "date": "2025-03-27",
        "date_epoch": 1743033600,
        "day": {
          "maxtemp_c": 9.7,
          "maxtemp_f": 49.4,
          "mintemp_c": 5.1,
          "mintemp_f": 41.1,
          "avgtemp_c": 7.1,
          "avgtemp_f": 44.8,
          "maxwind_mph": 7.4,
          "maxwind_kph": 11.9,
          "totalprecip_mm": 16.16,
          "totalprecip_in": 0.64,
          "totalsnow_cm": 0,
          "avgvis_km": 7,
          "avgvis_miles": 4,
          "avghumidity": 89,
          "daily_will_it_rain": 1,
          "daily_chance_of_rain": 89,
          "daily_will_it_snow": 0,
          "daily_chance_of_snow": 0,
          "condition": {
            "text": "Lluvia moderada",
            "icon": "//cdn.weatherapi.com/weather/64x64/day/302.png",
            "code": 1189
          },
          "uv": 0.1
        },
        "astro": {
          "sunrise": "05:53 AM",
          "sunset": "06:21 PM",
          "moonrise": "04:55 AM",
          "moonset": "04:04 PM",
          "moon_phase": "Waning Crescent",
          "moon_illumination": 9,
          "is_moon_up": 0,
          "is_sun_up": 0
        },
        "hour": [
          {
            "time_epoch": 1743030000,
            "time": "2025-03-27 00:00",
            "temp_c": 5.3,
            "temp_f": 41.5,
            "is_day": 0,
            "condition": {
              "text": "Parcialmente nublado",
              "icon": "//cdn.weatherapi.com/weather/64x64/night/116.png",
              "code": 1003
            },
            "wind_mph": 3.8,
            "wind_kph": 6.1,
            "wind_degree": 346,
            "wind_dir": "NNW",
            "pressure_mb": 1009,
            "pressure_in": 29.79,
            "precip_mm": 0,
            "precip_in": 0,
            "snow_cm": 0,
            "humidity": 93,
            "cloud": 37,
            "feelslike_c": 4,
            "feelslike_f": 39.2,
            "windchill_c": 4,
            "windchill_f": 39.2,
            "heatindex_c": 5.3,
            "heatindex_f": 41.5,
            "dewpoint_c": 4.3,
            "dewpoint_f": 39.7,
            "will_it_rain": 0,
            "chance_of_rain": 0,
            "will_it_snow": 0,
            "chance_of_snow": 0,
            "vis_km": 10,
            "vis_miles": 6,
            "gust_mph": 7.4,
            "gust_kph": 11.9,
            "uv": 0
          },
          {
            "time_epoch": 1743033600,
            "time": "2025-03-27 01:00",
            "temp_c": 5.1,
            "temp_f": 41.1,
            "is_day": 0,
            "condition": {
              "text": "Parcialmente nublado",
              "icon": "//cdn.weatherapi.com/weather/64x64/night/116.png",
              "code": 1003
            },
            "wind_mph": 2.7,
            "wind_kph": 4.3,
            "wind_degree": 336,
            "wind_dir": "NNW",
            "pressure_mb": 1009,
            "pressure_in": 29.79,
            "precip_mm": 0,
            "precip_in": 0,
            "snow_cm": 0,
            "humidity": 94,
            "cloud": 50,
            "feelslike_c": 4.4,
            "feelslike_f": 40,
            "windchill_c": 4.4,
            "windchill_f": 40,
            "heatindex_c": 5.1,
            "heatindex_f": 41.1,
            "dewpoint_c": 4.2,
            "dewpoint_f": 39.5,
            "will_it_rain": 0,
            "chance_of_rain": 0,
            "will_it_snow": 0,
            "chance_of_snow": 0,
            "vis_km": 10,
            "vis_miles": 6,
            "gust_mph": 5.2,
            "gust_kph": 8.3,
            "uv": 0
          },
          {
            "time_epoch": 1743037200,
            "time": "2025-03-27 02:00",
            "temp_c": 5.4,
            "temp_f": 41.7,
            "is_day": 0,
            "condition": {
              "text": "Lluvia  moderada a intervalos",
              "icon": "//cdn.weatherapi.com/weather/64x64/night/176.png",
              "code": 1063
            },
            "wind_mph": 3.6,
            "wind_kph": 5.8,
            "wind_degree": 307,
            "wind_dir": "NW",
            "pressure_mb": 1008,
            "pressure_in": 29.75,
            "precip_mm": 0.05,
            "precip_in": 0,
            "snow_cm": 0,
            "humidity": 93,
            "cloud": 55,
            "feelslike_c": 4.2,
            "feelslike_f": 39.6,
            "windchill_c": 4.2,
            "windchill_f": 39.6,
            "heatindex_c": 5.4,
            "heatindex_f": 41.7,
            "dewpoint_c": 4.4,
            "dewpoint_f": 39.9,
            "will_it_rain": 1,
            "chance_of_rain": 88,
            "will_it_snow": 0,
            "chance_of_snow": 0,
            "vis_km": 10,
            "vis_miles": 6,
            "gust_mph": 6.6,
            "gust_kph": 10.6,
            "uv": 0
          },
          {
            "time_epoch": 1743040800,
            "time": "2025-03-27 03:00",
            "temp_c": 5.6,
            "temp_f": 42.2,
            "is_day": 0,
            "condition": {
              "text": "Lluvia  moderada a intervalos",
              "icon": "//cdn.weatherapi.com/weather/64x64/night/176.png",
              "code": 1063
            },
            "wind_mph": 4.3,
            "wind_kph": 6.8,
            "wind_degree": 307,
            "wind_dir": "NW",
            "pressure_mb": 1006,
            "pressure_in": 29.72,
            "precip_mm": 0.12,
            "precip_in": 0,
            "snow_cm": 0,
            "humidity": 93,
            "cloud": 73,
            "feelslike_c": 4.2,
            "feelslike_f": 39.6,
            "windchill_c": 4.2,
            "windchill_f": 39.6,
            "heatindex_c": 5.7,
            "heatindex_f": 42.2,
            "dewpoint_c": 4.5,
            "dewpoint_f": 40.2,
            "will_it_rain": 1,
            "chance_of_rain": 100,
            "will_it_snow": 0,
            "chance_of_snow": 0,
            "vis_km": 10,
            "vis_miles": 6,
            "gust_mph": 7.7,
            "gust_kph": 12.4,
            "uv": 0
          },
          {
            "time_epoch": 1743044400,
            "time": "2025-03-27 04:00",
            "temp_c": 6.3,
            "temp_f": 43.3,
            "is_day": 0,
            "condition": {
              "text": "Nublado",
              "icon": "//cdn.weatherapi.com/weather/64x64/night/119.png",
              "code": 1006
            },
            "wind_mph": 3.8,
            "wind_kph": 6.1,
            "wind_degree": 308,
            "wind_dir": "NW",
            "pressure_mb": 1006,
            "pressure_in": 29.7,
            "precip_mm": 0,
            "precip_in": 0,
            "snow_cm": 0,
            "humidity": 90,
            "cloud": 84,
            "feelslike_c": 5.2,
            "feelslike_f": 41.3,
            "windchill_c": 5.2,
            "windchill_f": 41.3,
            "heatindex_c": 6.3,
            "heatindex_f": 43.3,
            "dewpoint_c": 4.8,
            "dewpoint_f": 40.7,
            "will_it_rain": 0,
            "chance_of_rain": 0,
            "will_it_snow": 0,
            "chance_of_snow": 0,
            "vis_km": 10,
            "vis_miles": 6,
            "gust_mph": 6.5,
            "gust_kph": 10.5,
            "uv": 0
          },
          {
            "time_epoch": 1743048000,
            "time": "2025-03-27 05:00",
            "temp_c": 6.6,
            "temp_f": 43.8,
            "is_day": 0,
            "condition": {
              "text": "Nublado",
              "icon": "//cdn.weatherapi.com/weather/64x64/night/119.png",
              "code": 1006
            },
            "wind_mph": 2.7,
            "wind_kph": 4.3,
            "wind_degree": 299,
            "wind_dir": "WNW",
            "pressure_mb": 1005,
            "pressure_in": 29.69,
            "precip_mm": 0,
            "precip_in": 0,
            "snow_cm": 0,
            "humidity": 88,
            "cloud": 75,
            "feelslike_c": 6.1,
            "feelslike_f": 43,
            "windchill_c": 6.1,
            "windchill_f": 43,
            "heatindex_c": 6.6,
            "heatindex_f": 43.8,
            "dewpoint_c": 4.7,
            "dewpoint_f": 40.5,
            "will_it_rain": 0,
            "chance_of_rain": 0,
            "will_it_snow": 0,
            "chance_of_snow": 0,
            "vis_km": 10,
            "vis_miles": 6,
            "gust_mph": 4.6,
            "gust_kph": 7.4,
            "uv": 0
          },
          {
            "time_epoch": 1743051600,
            "time": "2025-03-27 06:00",
            "temp_c": 6.6,
            "temp_f": 43.8,
            "is_day": 1,
            "condition": {
              "text": "Lluvia  moderada a intervalos",
              "icon": "//cdn.weatherapi.com/weather/64x64/day/176.png",
              "code": 1063
            },
            "wind_mph": 3.1,
            "wind_kph": 5,
            "wind_degree": 289,
            "wind_dir": "WNW",
            "pressure_mb": 1005,
            "pressure_in": 29.68,
            "precip_mm": 0.03,
            "precip_in": 0,
            "snow_cm": 0,
            "humidity": 87,
            "cloud": 56,
            "feelslike_c": 5.8,
            "feelslike_f": 42.5,
            "windchill_c": 5.8,
            "windchill_f": 42.5,
            "heatindex_c": 6.6,
            "heatindex_f": 43.8,
            "dewpoint_c": 4.6,
            "dewpoint_f": 40.3,
            "will_it_rain": 0,
            "chance_of_rain": 59,
            "will_it_snow": 0,
            "chance_of_snow": 0,
            "vis_km": 10,
            "vis_miles": 6,
            "gust_mph": 5.3,
            "gust_kph": 8.6,
            "uv": 0
          },
          {
            "time_epoch": 1743055200,
            "time": "2025-03-27 07:00",
            "temp_c": 7,
            "temp_f": 44.5,
            "is_day": 1,
            "condition": {
              "text": "Lluvia  moderada a intervalos",
              "icon": "//cdn.weatherapi.com/weather/64x64/day/176.png",
              "code": 1063
            },
            "wind_mph": 2.9,
            "wind_kph": 4.7,
            "wind_degree": 270,
            "wind_dir": "W",
            "pressure_mb": 1005,
            "pressure_in": 29.68,
            "precip_mm": 0.03,
            "precip_in": 0,
            "snow_cm": 0,
            "humidity": 87,
            "cloud": 100,
            "feelslike_c": 6.4,
            "feelslike_f": 43.6,
            "windchill_c": 6.4,
            "windchill_f": 43.6,
            "heatindex_c": 7,
            "heatindex_f": 44.5,
            "dewpoint_c": 4.9,
            "dewpoint_f": 40.8,
            "will_it_rain": 0,
            "chance_of_rain": 60,
            "will_it_snow": 0,
            "chance_of_snow": 0,
            "vis_km": 10,
            "vis_miles": 6,
            "gust_mph": 4.6,
            "gust_kph": 7.4,
            "uv": 0
          },
          {
            "time_epoch": 1743058800,
            "time": "2025-03-27 08:00",
            "temp_c": 7.6,
            "temp_f": 45.7,
            "is_day": 1,
            "condition": {
              "text": "Lluvia  moderada a intervalos",
              "icon": "//cdn.weatherapi.com/weather/64x64/day/176.png",
              "code": 1063
            },
            "wind_mph": 3.1,
            "wind_kph": 5,
            "wind_degree": 254,
            "wind_dir": "WSW",
            "pressure_mb": 1005,
            "pressure_in": 29.68,
            "precip_mm": 0.02,
            "precip_in": 0,
            "snow_cm": 0,
            "humidity": 84,
            "cloud": 100,
            "feelslike_c": 7,
            "feelslike_f": 44.6,
            "windchill_c": 7,
            "windchill_f": 44.6,
            "heatindex_c": 7.6,
            "heatindex_f": 45.7,
            "dewpoint_c": 5.1,
            "dewpoint_f": 41.1,
            "will_it_rain": 0,
            "chance_of_rain": 61,
            "will_it_snow": 0,
            "chance_of_snow": 0,
            "vis_km": 10,
            "vis_miles": 6,
            "gust_mph": 4.6,
            "gust_kph": 7.4,
            "uv": 0.1
          },
          {
            "time_epoch": 1743062400,
            "time": "2025-03-27 09:00",
            "temp_c": 8.8,
            "temp_f": 47.8,
            "is_day": 1,
            "condition": {
              "text": "Lluvia  moderada a intervalos",
              "icon": "//cdn.weatherapi.com/weather/64x64/day/176.png",
              "code": 1063
            },
            "wind_mph": 2.9,
            "wind_kph": 4.7,
            "wind_degree": 247,
            "wind_dir": "WSW",
            "pressure_mb": 1005,
            "pressure_in": 29.67,
            "precip_mm": 0.09,
            "precip_in": 0,
            "snow_cm": 0,
            "humidity": 78,
            "cloud": 100,
            "feelslike_c": 8.5,
            "feelslike_f": 47.2,
            "windchill_c": 8.5,
            "windchill_f": 47.2,
            "heatindex_c": 8.8,
            "heatindex_f": 47.8,
            "dewpoint_c": 5.1,
            "dewpoint_f": 41.2,
            "will_it_rain": 1,
            "chance_of_rain": 100,
            "will_it_snow": 0,
            "chance_of_snow": 0,
            "vis_km": 10,
            "vis_miles": 6,
            "gust_mph": 3.8,
            "gust_kph": 6,
            "uv": 0.2
          },
          {
            "time_epoch": 1743066000,
            "time": "2025-03-27 10:00",
            "temp_c": 9.6,
            "temp_f": 49.3,
            "is_day": 1,
            "condition": {
              "text": "Llovizna",
              "icon": "//cdn.weatherapi.com/weather/64x64/day/266.png",
              "code": 1153
            },
            "wind_mph": 3.6,
            "wind_kph": 5.8,
            "wind_degree": 259,
            "wind_dir": "W",
            "pressure_mb": 1004,
            "pressure_in": 29.65,
            "precip_mm": 0.32,
            "precip_in": 0.01,
            "snow_cm": 0,
            "humidity": 74,
            "cloud": 94,
            "feelslike_c": 9.1,
            "feelslike_f": 48.4,
            "windchill_c": 9.1,
            "windchill_f": 48.4,
            "heatindex_c": 9.6,
            "heatindex_f": 49.3,
            "dewpoint_c": 5.3,
            "dewpoint_f": 41.5,
            "will_it_rain": 1,
            "chance_of_rain": 100,
            "will_it_snow": 0,
            "chance_of_snow": 0,
            "vis_km": 2,
            "vis_miles": 1,
            "gust_mph": 4.4,
            "gust_kph": 7.1,
            "uv": 0.4
          },
          {
            "time_epoch": 1743069600,
            "time": "2025-03-27 11:00",
            "temp_c": 9.7,
            "temp_f": 49.4,
            "is_day": 1,
            "condition": {
              "text": "Llovizna",
              "icon": "//cdn.weatherapi.com/weather/64x64/day/266.png",
              "code": 1153
            },
            "wind_mph": 4.5,
            "wind_kph": 7.2,
            "wind_degree": 274,
            "wind_dir": "W",
            "pressure_mb": 1004,
            "pressure_in": 29.64,
            "precip_mm": 0.65,
            "precip_in": 0.03,
            "snow_cm": 0,
            "humidity": 76,
            "cloud": 100,
            "feelslike_c": 8.8,
            "feelslike_f": 47.8,
            "windchill_c": 8.8,
            "windchill_f": 47.8,
            "heatindex_c": 9.7,
            "heatindex_f": 49.4,
            "dewpoint_c": 5.7,
            "dewpoint_f": 42.3,
            "will_it_rain": 1,
            "chance_of_rain": 100,
            "will_it_snow": 0,
            "chance_of_snow": 0,
            "vis_km": 2,
            "vis_miles": 1,
            "gust_mph": 5.5,
            "gust_kph": 8.9,
            "uv": 0.6
          },
          {
            "time_epoch": 1743073200,
            "time": "2025-03-27 12:00",
            "temp_c": 9.1,
            "temp_f": 48.3,
            "is_day": 1,
            "condition": {
              "text": "Llovizna",
              "icon": "//cdn.weatherapi.com/weather/64x64/day/266.png",
              "code": 1153
            },
            "wind_mph": 6.5,
            "wind_kph": 10.4,
            "wind_degree": 269,
            "wind_dir": "W",
            "pressure_mb": 1003,
            "pressure_in": 29.63,
            "precip_mm": 0.64,
            "precip_in": 0.03,
            "snow_cm": 0,
            "humidity": 81,
            "cloud": 100,
            "feelslike_c": 7.4,
            "feelslike_f": 45.4,
            "windchill_c": 7.4,
            "windchill_f": 45.4,
            "heatindex_c": 9.1,
            "heatindex_f": 48.3,
            "dewpoint_c": 6,
            "dewpoint_f": 42.7,
            "will_it_rain": 1,
            "chance_of_rain": 100,
            "will_it_snow": 0,
            "chance_of_snow": 0,
            "vis_km": 2,
            "vis_miles": 1,
            "gust_mph": 8.5,
            "gust_kph": 13.6,
            "uv": 0.7
          },
          {
            "time_epoch": 1743076800,
            "time": "2025-03-27 13:00",
            "temp_c": 8.9,
            "temp_f": 47.9,
            "is_day": 1,
            "condition": {
              "text": "Llovizna",
              "icon": "//cdn.weatherapi.com/weather/64x64/day/266.png",
              "code": 1153
            },
            "wind_mph": 7.4,
            "wind_kph": 11.9,
            "wind_degree": 260,
            "wind_dir": "W",
            "pressure_mb": 1003,
            "pressure_in": 29.61,
            "precip_mm": 0.66,
            "precip_in": 0.03,
            "snow_cm": 0,
            "humidity": 81,
            "cloud": 100,
            "feelslike_c": 7,
            "feelslike_f": 44.5,
            "windchill_c": 7,
            "windchill_f": 44.5,
            "heatindex_c": 8.9,
            "heatindex_f": 47.9,
            "dewpoint_c": 5.8,
            "dewpoint_f": 42.5,
            "will_it_rain": 1,
            "chance_of_rain": 100,
            "will_it_snow": 0,
            "chance_of_snow": 0,
            "vis_km": 2,
            "vis_miles": 1,
            "gust_mph": 9.9,
            "gust_kph": 15.9,
            "uv": 0.5
          },
          {
            "time_epoch": 1743080400,
            "time": "2025-03-27 14:00",
            "temp_c": 8.8,
            "temp_f": 47.9,
            "is_day": 1,
            "condition": {
              "text": "Ligeras lluvias",
              "icon": "//cdn.weatherapi.com/weather/64x64/day/296.png",
              "code": 1183
            },
            "wind_mph": 6.7,
            "wind_kph": 10.8,
            "wind_degree": 257,
            "wind_dir": "WSW",
            "pressure_mb": 1002,
            "pressure_in": 29.6,
            "precip_mm": 2.1,
            "precip_in": 0.08,
            "snow_cm": 0,
            "humidity": 84,
            "cloud": 100,
            "feelslike_c": 7.1,
            "feelslike_f": 44.7,
            "windchill_c": 7.1,
            "windchill_f": 44.7,
            "heatindex_c": 8.8,
            "heatindex_f": 47.9,
            "dewpoint_c": 6.3,
            "dewpoint_f": 43.3,
            "will_it_rain": 1,
            "chance_of_rain": 100,
            "will_it_snow": 0,
            "chance_of_snow": 0,
            "vis_km": 9,
            "vis_miles": 5,
            "gust_mph": 8.6,
            "gust_kph": 13.8,
            "uv": 0.5
          },
          {
            "time_epoch": 1743084000,
            "time": "2025-03-27 15:00",
            "temp_c": 7.8,
            "temp_f": 46.1,
            "is_day": 1,
            "condition": {
              "text": "Lluvia moderada",
              "icon": "//cdn.weatherapi.com/weather/64x64/day/302.png",
              "code": 1189
            },
            "wind_mph": 6,
            "wind_kph": 9.7,
            "wind_degree": 250,
            "wind_dir": "WSW",
            "pressure_mb": 1002,
            "pressure_in": 29.6,
            "precip_mm": 3.78,
            "precip_in": 0.15,
            "snow_cm": 0,
            "humidity": 93,
            "cloud": 100,
            "feelslike_c": 6.1,
            "feelslike_f": 42.9,
            "windchill_c": 6.1,
            "windchill_f": 42.9,
            "heatindex_c": 7.8,
            "heatindex_f": 46.1,
            "dewpoint_c": 6.7,
            "dewpoint_f": 44,
            "will_it_rain": 1,
            "chance_of_rain": 100,
            "will_it_snow": 0,
            "chance_of_snow": 0,
            "vis_km": 7,
            "vis_miles": 4,
            "gust_mph": 8.3,
            "gust_kph": 13.4,
            "uv": 0.2
          },
          {
            "time_epoch": 1743087600,
            "time": "2025-03-27 16:00",
            "temp_c": 7.4,
            "temp_f": 45.4,
            "is_day": 1,
            "condition": {
              "text": "Lluvia moderada",
              "icon": "//cdn.weatherapi.com/weather/64x64/day/302.png",
              "code": 1189
            },
            "wind_mph": 6.5,
            "wind_kph": 10.4,
            "wind_degree": 239,
            "wind_dir": "WSW",
            "pressure_mb": 1002,
            "pressure_in": 29.6,
            "precip_mm": 3.31,
            "precip_in": 0.13,
            "snow_cm": 0,
            "humidity": 94,
            "cloud": 100,
            "feelslike_c": 5.5,
            "feelslike_f": 41.8,
            "windchill_c": 5.5,
            "windchill_f": 41.8,
            "heatindex_c": 7.4,
            "heatindex_f": 45.4,
            "dewpoint_c": 6.5,
            "dewpoint_f": 43.7,
            "will_it_rain": 1,
            "chance_of_rain": 100,
            "will_it_snow": 0,
            "chance_of_snow": 0,
            "vis_km": 7,
            "vis_miles": 4,
            "gust_mph": 9,
            "gust_kph": 14.5,
            "uv": 0.1
          },
          {
            "time_epoch": 1743091200,
            "time": "2025-03-27 17:00",
            "temp_c": 7.1,
            "temp_f": 44.7,
            "is_day": 1,
            "condition": {
              "text": "Ligeras lluvias",
              "icon": "//cdn.weatherapi.com/weather/64x64/day/296.png",
              "code": 1183
            },
            "wind_mph": 7.2,
            "wind_kph": 11.5,
            "wind_degree": 235,
            "wind_dir": "SW",
            "pressure_mb": 1003,
            "pressure_in": 29.61,
            "precip_mm": 1.15,
            "precip_in": 0.05,
            "snow_cm": 0,
            "humidity": 93,
            "cloud": 100,
            "feelslike_c": 4.8,
            "feelslike_f": 40.7,
            "windchill_c": 4.8,
            "windchill_f": 40.7,
            "heatindex_c": 7.1,
            "heatindex_f": 44.7,
            "dewpoint_c": 6.1,
            "dewpoint_f": 42.9,
            "will_it_rain": 1,
            "chance_of_rain": 100,
            "will_it_snow": 0,
            "chance_of_snow": 0,
            "vis_km": 9,
            "vis_miles": 5,
            "gust_mph": 10.2,
            "gust_kph": 16.5,
            "uv": 0
          },
          {
            "time_epoch": 1743094800,
            "time": "2025-03-27 18:00",
            "temp_c": 6.7,
            "temp_f": 44.1,
            "is_day": 1,
            "condition": {
              "text": "Ligeras precipitaciones",
              "icon": "//cdn.weatherapi.com/weather/64x64/day/353.png",
              "code": 1240
            },
            "wind_mph": 6.5,
            "wind_kph": 10.4,
            "wind_degree": 241,
            "wind_dir": "WSW",
            "pressure_mb": 1003,
            "pressure_in": 29.62,
            "precip_mm": 0.44,
            "precip_in": 0.02,
            "snow_cm": 0,
            "humidity": 94,
            "cloud": 100,
            "feelslike_c": 4.6,
            "feelslike_f": 40.3,
            "windchill_c": 4.6,
            "windchill_f": 40.3,
            "heatindex_c": 6.7,
            "heatindex_f": 44.1,
            "dewpoint_c": 5.8,
            "dewpoint_f": 42.4,
            "will_it_rain": 1,
            "chance_of_rain": 100,
            "will_it_snow": 0,
            "chance_of_snow": 0,
            "vis_km": 10,
            "vis_miles": 6,
            "gust_mph": 9.4,
            "gust_kph": 15.1,
            "uv": 0
          },
          {
            "time_epoch": 1743098400,
            "time": "2025-03-27 19:00",
            "temp_c": 6.5,
            "temp_f": 43.7,
            "is_day": 0,
            "condition": {
              "text": "Ligeras precipitaciones",
              "icon": "//cdn.weatherapi.com/weather/64x64/night/353.png",
              "code": 1240
            },
            "wind_mph": 4.7,
            "wind_kph": 7.6,
            "wind_degree": 241,
            "wind_dir": "WSW",
            "pressure_mb": 1004,
            "pressure_in": 29.64,
            "precip_mm": 0.37,
            "precip_in": 0.01,
            "snow_cm": 0,
            "humidity": 95,
            "cloud": 100,
            "feelslike_c": 5,
            "feelslike_f": 41,
            "windchill_c": 5,
            "windchill_f": 41,
            "heatindex_c": 6.5,
            "heatindex_f": 43.7,
            "dewpoint_c": 5.7,
            "dewpoint_f": 42.2,
            "will_it_rain": 1,
            "chance_of_rain": 100,
            "will_it_snow": 0,
            "chance_of_snow": 0,
            "vis_km": 10,
            "vis_miles": 6,
            "gust_mph": 6.9,
            "gust_kph": 11.1,
            "uv": 0
          },
          {
            "time_epoch": 1743102000,
            "time": "2025-03-27 20:00",
            "temp_c": 6.4,
            "temp_f": 43.5,
            "is_day": 0,
            "condition": {
              "text": "Llovizna",
              "icon": "//cdn.weatherapi.com/weather/64x64/night/266.png",
              "code": 1153
            },
            "wind_mph": 4.7,
            "wind_kph": 7.6,
            "wind_degree": 240,
            "wind_dir": "WSW",
            "pressure_mb": 1004,
            "pressure_in": 29.66,
            "precip_mm": 0.42,
            "precip_in": 0.02,
            "snow_cm": 0,
            "humidity": 95,
            "cloud": 100,
            "feelslike_c": 4.9,
            "feelslike_f": 40.8,
            "windchill_c": 4.9,
            "windchill_f": 40.8,
            "heatindex_c": 6.4,
            "heatindex_f": 43.5,
            "dewpoint_c": 5.7,
            "dewpoint_f": 42.2,
            "will_it_rain": 1,
            "chance_of_rain": 100,
            "will_it_snow": 0,
            "chance_of_snow": 0,
            "vis_km": 2,
            "vis_miles": 1,
            "gust_mph": 6.9,
            "gust_kph": 11.1,
            "uv": 0
          },
          {
            "time_epoch": 1743105600,
            "time": "2025-03-27 21:00",
            "temp_c": 6.4,
            "temp_f": 43.5,
            "is_day": 0,
            "condition": {
              "text": "Llovizna",
              "icon": "//cdn.weatherapi.com/weather/64x64/night/266.png",
              "code": 1153
            },
            "wind_mph": 3.8,
            "wind_kph": 6.1,
            "wind_degree": 267,
            "wind_dir": "W",
            "pressure_mb": 1005,
            "pressure_in": 29.67,
            "precip_mm": 0.66,
            "precip_in": 0.03,
            "snow_cm": 0,
            "humidity": 96,
            "cloud": 100,
            "feelslike_c": 5.3,
            "feelslike_f": 41.6,
            "windchill_c": 5.3,
            "windchill_f": 41.6,
            "heatindex_c": 6.4,
            "heatindex_f": 43.5,
            "dewpoint_c": 5.8,
            "dewpoint_f": 42.5,
            "will_it_rain": 1,
            "chance_of_rain": 100,
            "will_it_snow": 0,
            "chance_of_snow": 0,
            "vis_km": 2,
            "vis_miles": 1,
            "gust_mph": 5.5,
            "gust_kph": 8.9,
            "uv": 0
          },
          {
            "time_epoch": 1743109200,
            "time": "2025-03-27 22:00",
            "temp_c": 6.5,
            "temp_f": 43.6,
            "is_day": 0,
            "condition": {
              "text": "Llovizna",
              "icon": "//cdn.weatherapi.com/weather/64x64/night/266.png",
              "code": 1153
            },
            "wind_mph": 5.1,
            "wind_kph": 8.3,
            "wind_degree": 307,
            "wind_dir": "NW",
            "pressure_mb": 1005,
            "pressure_in": 29.68,
            "precip_mm": 0.71,
            "precip_in": 0.03,
            "snow_cm": 0,
            "humidity": 97,
            "cloud": 100,
            "feelslike_c": 4.8,
            "feelslike_f": 40.6,
            "windchill_c": 4.8,
            "windchill_f": 40.6,
            "heatindex_c": 6.5,
            "heatindex_f": 43.6,
            "dewpoint_c": 6,
            "dewpoint_f": 42.7,
            "will_it_rain": 1,
            "chance_of_rain": 100,
            "will_it_snow": 0,
            "chance_of_snow": 0,
            "vis_km": 2,
            "vis_miles": 1,
            "gust_mph": 7.4,
            "gust_kph": 11.9,
            "uv": 0
          },
          {
            "time_epoch": 1743112800,
            "time": "2025-03-27 23:00",
            "temp_c": 6.4,
            "temp_f": 43.4,
            "is_day": 0,
            "condition": {
              "text": "Llovizna",
              "icon": "//cdn.weatherapi.com/weather/64x64/night/266.png",
              "code": 1153
            },
            "wind_mph": 4.7,
            "wind_kph": 7.6,
            "wind_degree": 330,
            "wind_dir": "NNW",
            "pressure_mb": 1005,
            "pressure_in": 29.69,
            "precip_mm": 0.61,
            "precip_in": 0.02,
            "snow_cm": 0,
            "humidity": 97,
            "cloud": 100,
            "feelslike_c": 4.8,
            "feelslike_f": 40.7,
            "windchill_c": 4.8,
            "windchill_f": 40.7,
            "heatindex_c": 6.4,
            "heatindex_f": 43.4,
            "dewpoint_c": 6,
            "dewpoint_f": 42.7,
            "will_it_rain": 1,
            "chance_of_rain": 100,
            "will_it_snow": 0,
            "chance_of_snow": 0,
            "vis_km": 2,
            "vis_miles": 1,
            "gust_mph": 6.8,
            "gust_kph": 10.9,
            "uv": 0
          }
        ]
      },
      {
        "date": "2025-03-28",
        "date_epoch": 1743120000,
        "day": {
          "maxtemp_c": 7.5,
          "maxtemp_f": 45.4,
          "mintemp_c": 6.2,
          "mintemp_f": 43.2,
          "avgtemp_c": 6.8,
          "avgtemp_f": 44.3,
          "maxwind_mph": 6,
          "maxwind_kph": 9.7,
          "totalprecip_mm": 5.89,
          "totalprecip_in": 0.23,
          "totalsnow_cm": 0,
          "avgvis_km": 6.3,
          "avgvis_miles": 3,
          "avghumidity": 93,
          "daily_will_it_rain": 1,
          "daily_chance_of_rain": 88,
          "daily_will_it_snow": 0,
          "daily_chance_of_snow": 0,
          "condition": {
            "text": "Lluvia moderada",
            "icon": "//cdn.weatherapi.com/weather/64x64/day/302.png",
            "code": 1189
          },
          "uv": 0.3
        },
        "astro": {
          "sunrise": "05:51 AM",
          "sunset": "06:22 PM",
          "moonrise": "05:19 AM",
          "moonset": "05:22 PM",
          "moon_phase": "Waning Crescent",
          "moon_illumination": 3,
          "is_moon_up": 0,
          "is_sun_up": 0
        },
        "hour": [
          {
            "time_epoch": 1743116400,
            "time": "2025-03-28 00:00",
            "temp_c": 6.5,
            "temp_f": 43.6,
            "is_day": 0,
            "condition": {
              "text": "Llovizna",
              "icon": "//cdn.weatherapi.com/weather/64x64/night/266.png",
              "code": 1153
            },
            "wind_mph": 4.3,
            "wind_kph": 6.8,
            "wind_degree": 349,
            "wind_dir": "N",
            "pressure_mb": 1006,
            "pressure_in": 29.7,
            "precip_mm": 0.22,
            "precip_in": 0.01,
            "snow_cm": 0,
            "humidity": 98,
            "cloud": 100,
            "feelslike_c": 5.2,
            "feelslike_f": 41.3,
            "windchill_c": 5.2,
            "windchill_f": 41.3,
            "heatindex_c": 6.5,
            "heatindex_f": 43.6,
            "dewpoint_c": 6.2,
            "dewpoint_f": 43.2,
            "will_it_rain": 1,
            "chance_of_rain": 100,
            "will_it_snow": 0,
            "chance_of_snow": 0,
            "vis_km": 2,
            "vis_miles": 1,
            "gust_mph": 6.1,
            "gust_kph": 9.9,
            "uv": 0
          },
          {
            "time_epoch": 1743120000,
            "time": "2025-03-28 01:00",
            "temp_c": 6.6,
            "temp_f": 43.8,
            "is_day": 0,
            "condition": {
              "text": "Llovizna",
              "icon": "//cdn.weatherapi.com/weather/64x64/night/266.png",
              "code": 1153
            },
            "wind_mph": 2.9,
            "wind_kph": 4.7,
            "wind_degree": 0,
            "wind_dir": "N",
            "pressure_mb": 1005,
            "pressure_in": 29.69,
            "precip_mm": 0.43,
            "precip_in": 0.02,
            "snow_cm": 0,
            "humidity": 99,
            "cloud": 100,
            "feelslike_c": 6,
            "feelslike_f": 42.8,
            "windchill_c": 6,
            "windchill_f": 42.8,
            "heatindex_c": 6.6,
            "heatindex_f": 43.8,
            "dewpoint_c": 6.4,
            "dewpoint_f": 43.5,
            "will_it_rain": 1,
            "chance_of_rain": 100,
            "will_it_snow": 0,
            "chance_of_snow": 0,
            "vis_km": 2,
            "vis_miles": 1,
            "gust_mph": 4.2,
            "gust_kph": 6.7,
            "uv": 0
          },
          {
            "time_epoch": 1743123600,
            "time": "2025-03-28 02:00",
            "temp_c": 6.6,
            "temp_f": 43.9,
            "is_day": 0,
            "condition": {
              "text": "Ligeras lluvias",
              "icon": "//cdn.weatherapi.com/weather/64x64/night/296.png",
              "code": 1183
            },
            "wind_mph": 2,
            "wind_kph": 3.2,
            "wind_degree": 338,
            "wind_dir": "NNW",
            "pressure_mb": 1005,
            "pressure_in": 29.67,
            "precip_mm": 0.92,
            "precip_in": 0.04,
            "snow_cm": 0,
            "humidity": 98,
            "cloud": 100,
            "feelslike_c": 6.7,
            "feelslike_f": 44,
            "windchill_c": 6.7,
            "windchill_f": 44,
            "heatindex_c": 6.6,
            "heatindex_f": 43.9,
            "dewpoint_c": 6.4,
            "dewpoint_f": 43.5,
            "will_it_rain": 1,
            "chance_of_rain": 100,
            "will_it_snow": 0,
            "chance_of_snow": 0,
            "vis_km": 9,
            "vis_miles": 5,
            "gust_mph": 2.9,
            "gust_kph": 4.7,
            "uv": 0
          },
          {
            "time_epoch": 1743127200,
            "time": "2025-03-28 03:00",
            "temp_c": 6.5,
            "temp_f": 43.7,
            "is_day": 0,
            "condition": {
              "text": "Ligeras lluvias",
              "icon": "//cdn.weatherapi.com/weather/64x64/night/296.png",
              "code": 1183
            },
            "wind_mph": 2.2,
            "wind_kph": 3.6,
            "wind_degree": 330,
            "wind_dir": "NNW",
            "pressure_mb": 1004,
            "pressure_in": 29.66,
            "precip_mm": 1.01,
            "precip_in": 0.04,
            "snow_cm": 0,
            "humidity": 99,
            "cloud": 100,
            "feelslike_c": 6.4,
            "feelslike_f": 43.5,
            "windchill_c": 6.4,
            "windchill_f": 43.5,
            "heatindex_c": 6.5,
            "heatindex_f": 43.7,
            "dewpoint_c": 6.3,
            "dewpoint_f": 43.3,
            "will_it_rain": 1,
            "chance_of_rain": 100,
            "will_it_snow": 0,
            "chance_of_snow": 0,
            "vis_km": 9,
            "vis_miles": 5,
            "gust_mph": 3.4,
            "gust_kph": 5.4,
            "uv": 0
          },
          {
            "time_epoch": 1743130800,
            "time": "2025-03-28 04:00",
            "temp_c": 6.6,
            "temp_f": 43.9,
            "is_day": 0,
            "condition": {
              "text": "Llovizna",
              "icon": "//cdn.weatherapi.com/weather/64x64/night/266.png",
              "code": 1153
            },
            "wind_mph": 2.9,
            "wind_kph": 4.7,
            "wind_degree": 327,
            "wind_dir": "NNW",
            "pressure_mb": 1004,
            "pressure_in": 29.66,
            "precip_mm": 0.67,
            "precip_in": 0.03,
            "snow_cm": 0,
            "humidity": 99,
            "cloud": 100,
            "feelslike_c": 6,
            "feelslike_f": 42.8,
            "windchill_c": 6,
            "windchill_f": 42.8,
            "heatindex_c": 6.6,
            "heatindex_f": 43.9,
            "dewpoint_c": 6.4,
            "dewpoint_f": 43.5,
            "will_it_rain": 1,
            "chance_of_rain": 100,
            "will_it_snow": 0,
            "chance_of_snow": 0,
            "vis_km": 2,
            "vis_miles": 1,
            "gust_mph": 4.4,
            "gust_kph": 7.1,
            "uv": 0
          },
          {
            "time_epoch": 1743134400,
            "time": "2025-03-28 05:00",
            "temp_c": 6.6,
            "temp_f": 44,
            "is_day": 0,
            "condition": {
              "text": "Llovizna",
              "icon": "//cdn.weatherapi.com/weather/64x64/night/266.png",
              "code": 1153
            },
            "wind_mph": 3.6,
            "wind_kph": 5.8,
            "wind_degree": 321,
            "wind_dir": "NW",
            "pressure_mb": 1004,
            "pressure_in": 29.66,
            "precip_mm": 0.39,
            "precip_in": 0.02,
            "snow_cm": 0,
            "humidity": 98,
            "cloud": 100,
            "feelslike_c": 5.7,
            "feelslike_f": 42.2,
            "windchill_c": 5.7,
            "windchill_f": 42.2,
            "heatindex_c": 6.6,
            "heatindex_f": 44,
            "dewpoint_c": 6.4,
            "dewpoint_f": 43.4,
            "will_it_rain": 1,
            "chance_of_rain": 100,
            "will_it_snow": 0,
            "chance_of_snow": 0,
            "vis_km": 2,
            "vis_miles": 1,
            "gust_mph": 5.5,
            "gust_kph": 8.8,
            "uv": 0
          },
          {
            "time_epoch": 1743138000,
            "time": "2025-03-28 06:00",
            "temp_c": 6.6,
            "temp_f": 43.9,
            "is_day": 1,
            "condition": {
              "text": "Ligeras precipitaciones",
              "icon": "//cdn.weatherapi.com/weather/64x64/day/353.png",
              "code": 1240
            },
            "wind_mph": 4,
            "wind_kph": 6.5,
            "wind_degree": 327,
            "wind_dir": "NNW",
            "pressure_mb": 1005,
            "pressure_in": 29.66,
            "precip_mm": 0.42,
            "precip_in": 0.02,
            "snow_cm": 0,
            "humidity": 98,
            "cloud": 100,
            "feelslike_c": 5.5,
            "feelslike_f": 41.8,
            "windchill_c": 5.5,
            "windchill_f": 41.8,
            "heatindex_c": 6.6,
            "heatindex_f": 43.9,
            "dewpoint_c": 6.3,
            "dewpoint_f": 43.3,
            "will_it_rain": 1,
            "chance_of_rain": 100,
            "will_it_snow": 0,
            "chance_of_snow": 0,
            "vis_km": 10,
            "vis_miles": 6,
            "gust_mph": 6.2,
            "gust_kph": 10,
            "uv": 0
          },
          {
            "time_epoch": 1743141600,
            "time": "2025-03-28 07:00",
            "temp_c": 6.7,
            "temp_f": 44,
            "is_day": 1,
            "condition": {
              "text": "Neblina",
              "icon": "//cdn.weatherapi.com/weather/64x64/day/143.png",
              "code": 1030
            },
            "wind_mph": 4.7,
            "wind_kph": 7.6,
            "wind_degree": 327,
            "wind_dir": "NNW",
            "pressure_mb": 1005,
            "pressure_in": 29.68,
            "precip_mm": 0.15,
            "precip_in": 0.01,
            "snow_cm": 0,
            "humidity": 96,
            "cloud": 100,
            "feelslike_c": 5.2,
            "feelslike_f": 41.4,
            "windchill_c": 5.2,
            "windchill_f": 41.4,
            "heatindex_c": 6.7,
            "heatindex_f": 44,
            "dewpoint_c": 6.2,
            "dewpoint_f": 43.1,
            "will_it_rain": 1,
            "chance_of_rain": 100,
            "will_it_snow": 0,
            "chance_of_snow": 0,
            "vis_km": 2,
            "vis_miles": 1,
            "gust_mph": 7.3,
            "gust_kph": 11.7,
            "uv": 0
          },
          {
            "time_epoch": 1743145200,
            "time": "2025-03-28 08:00",
            "temp_c": 7,
            "temp_f": 44.5,
            "is_day": 1,
            "condition": {
              "text": "Neblina",
              "icon": "//cdn.weatherapi.com/weather/64x64/day/143.png",
              "code": 1030
            },
            "wind_mph": 4.7,
            "wind_kph": 7.6,
            "wind_degree": 316,
            "wind_dir": "NW",
            "pressure_mb": 1005,
            "pressure_in": 29.68,
            "precip_mm": 0.12,
            "precip_in": 0,
            "snow_cm": 0,
            "humidity": 94,
            "cloud": 100,
            "feelslike_c": 5.5,
            "feelslike_f": 42,
            "windchill_c": 5.5,
            "windchill_f": 42,
            "heatindex_c": 7,
            "heatindex_f": 44.5,
            "dewpoint_c": 6.1,
            "dewpoint_f": 42.9,
            "will_it_rain": 1,
            "chance_of_rain": 100,
            "will_it_snow": 0,
            "chance_of_snow": 0,
            "vis_km": 2,
            "vis_miles": 1,
            "gust_mph": 7.1,
            "gust_kph": 11.4,
            "uv": 0.1
          },
          {
            "time_epoch": 1743148800,
            "time": "2025-03-28 09:00",
            "temp_c": 7.3,
            "temp_f": 45.2,
            "is_day": 1,
            "condition": {
              "text": "Lluvia  moderada a intervalos",
              "icon": "//cdn.weatherapi.com/weather/64x64/day/176.png",
              "code": 1063
            },
            "wind_mph": 5.6,
            "wind_kph": 9,
            "wind_degree": 310,
            "wind_dir": "NW",
            "pressure_mb": 1005,
            "pressure_in": 29.68,
            "precip_mm": 0.08,
            "precip_in": 0,
            "snow_cm": 0,
            "humidity": 90,
            "cloud": 100,
            "feelslike_c": 5.6,
            "feelslike_f": 42.2,
            "windchill_c": 5.6,
            "windchill_f": 42.2,
            "heatindex_c": 7.3,
            "heatindex_f": 45.2,
            "dewpoint_c": 5.8,
            "dewpoint_f": 42.5,
            "will_it_rain": 1,
            "chance_of_rain": 100,
            "will_it_snow": 0,
            "chance_of_snow": 0,
            "vis_km": 10,
            "vis_miles": 6,
            "gust_mph": 8,
            "gust_kph": 12.9,
            "uv": 0.3
          },
          {
            "time_epoch": 1743152400,
            "time": "2025-03-28 10:00",
            "temp_c": 7.4,
            "temp_f": 45.4,
            "is_day": 1,
            "condition": {
              "text": "Lluvia  moderada a intervalos",
              "icon": "//cdn.weatherapi.com/weather/64x64/day/176.png",
              "code": 1063
            },
            "wind_mph": 6,
            "wind_kph": 9.7,
            "wind_degree": 309,
            "wind_dir": "NW",
            "pressure_mb": 1005,
            "pressure_in": 29.68,
            "precip_mm": 0.03,
            "precip_in": 0,
            "snow_cm": 0,
            "humidity": 88,
            "cloud": 100,
            "feelslike_c": 5.6,
            "feelslike_f": 42.2,
            "windchill_c": 5.6,
            "windchill_f": 42.2,
            "heatindex_c": 7.5,
            "heatindex_f": 45.4,
            "dewpoint_c": 5.6,
            "dewpoint_f": 42,
            "will_it_rain": 0,
            "chance_of_rain": 67,
            "will_it_snow": 0,
            "chance_of_snow": 0,
            "vis_km": 10,
            "vis_miles": 6,
            "gust_mph": 8.3,
            "gust_kph": 13.4,
            "uv": 0.5
          },
          {
            "time_epoch": 1743156000,
            "time": "2025-03-28 11:00",
            "temp_c": 7.4,
            "temp_f": 45.4,
            "is_day": 1,
            "condition": {
              "text": "Lluvia  moderada a intervalos",
              "icon": "//cdn.weatherapi.com/weather/64x64/day/176.png",
              "code": 1063
            },
            "wind_mph": 5.1,
            "wind_kph": 8.3,
            "wind_degree": 315,
            "wind_dir": "NW",
            "pressure_mb": 1005,
            "pressure_in": 29.69,
            "precip_mm": 0.09,
            "precip_in": 0,
            "snow_cm": 0,
            "humidity": 86,
            "cloud": 100,
            "feelslike_c": 5.9,
            "feelslike_f": 42.7,
            "windchill_c": 5.9,
            "windchill_f": 42.7,
            "heatindex_c": 7.4,
            "heatindex_f": 45.4,
            "dewpoint_c": 5.3,
            "dewpoint_f": 41.5,
            "will_it_rain": 1,
            "chance_of_rain": 100,
            "will_it_snow": 0,
            "chance_of_snow": 0,
            "vis_km": 10,
            "vis_miles": 6,
            "gust_mph": 7,
            "gust_kph": 11.3,
            "uv": 0.9
          },
          {
            "time_epoch": 1743159600,
            "time": "2025-03-28 12:00",
            "temp_c": 7.2,
            "temp_f": 45,
            "is_day": 1,
            "condition": {
              "text": "Lluvia  moderada a intervalos",
              "icon": "//cdn.weatherapi.com/weather/64x64/day/176.png",
              "code": 1063
            },
            "wind_mph": 4.9,
            "wind_kph": 7.9,
            "wind_degree": 308,
            "wind_dir": "NW",
            "pressure_mb": 1005,
            "pressure_in": 29.68,
            "precip_mm": 0.08,
            "precip_in": 0,
            "snow_cm": 0,
            "humidity": 88,
            "cloud": 100,
            "feelslike_c": 5.8,
            "feelslike_f": 42.4,
            "windchill_c": 5.8,
            "windchill_f": 42.4,
            "heatindex_c": 7.2,
            "heatindex_f": 45,
            "dewpoint_c": 5.4,
            "dewpoint_f": 41.7,
            "will_it_rain": 1,
            "chance_of_rain": 100,
            "will_it_snow": 0,
            "chance_of_snow": 0,
            "vis_km": 10,
            "vis_miles": 6,
            "gust_mph": 6.9,
            "gust_kph": 11.1,
            "uv": 1.3
          },
          {
            "time_epoch": 1743163200,
            "time": "2025-03-28 13:00",
            "temp_c": 7.2,
            "temp_f": 45,
            "is_day": 1,
            "condition": {
              "text": "Lluvia  moderada a intervalos",
              "icon": "//cdn.weatherapi.com/weather/64x64/day/176.png",
              "code": 1063
            },
            "wind_mph": 5.4,
            "wind_kph": 8.6,
            "wind_degree": 312,
            "wind_dir": "NW",
            "pressure_mb": 1005,
            "pressure_in": 29.68,
            "precip_mm": 0.01,
            "precip_in": 0,
            "snow_cm": 0,
            "humidity": 87,
            "cloud": 100,
            "feelslike_c": 5.6,
            "feelslike_f": 42.1,
            "windchill_c": 5.6,
            "windchill_f": 42.1,
            "heatindex_c": 7.2,
            "heatindex_f": 45,
            "dewpoint_c": 5.3,
            "dewpoint_f": 41.5,
            "will_it_rain": 1,
            "chance_of_rain": 88,
            "will_it_snow": 0,
            "chance_of_snow": 0,
            "vis_km": 10,
            "vis_miles": 6,
            "gust_mph": 7.6,
            "gust_kph": 12.2,
            "uv": 1.6
          },
          {
            "time_epoch": 1743166800,
            "time": "2025-03-28 14:00",
            "temp_c": 7.5,
            "temp_f": 45.4,
            "is_day": 1,
            "condition": {
              "text": "Lluvia  moderada a intervalos",
              "icon": "//cdn.weatherapi.com/weather/64x64/day/176.png",
              "code": 1063
            },
            "wind_mph": 4.5,
            "wind_kph": 7.2,
            "wind_degree": 325,
            "wind_dir": "NW",
            "pressure_mb": 1005,
            "pressure_in": 29.68,
            "precip_mm": 0.12,
            "precip_in": 0,
            "snow_cm": 0,
            "humidity": 88,
            "cloud": 100,
            "feelslike_c": 6.2,
            "feelslike_f": 43.2,
            "windchill_c": 6.2,
            "windchill_f": 43.2,
            "heatindex_c": 7.5,
            "heatindex_f": 45.4,
            "dewpoint_c": 5.6,
            "dewpoint_f": 42,
            "will_it_rain": 1,
            "chance_of_rain": 100,
            "will_it_snow": 0,
            "chance_of_snow": 0,
            "vis_km": 10,
            "vis_miles": 6,
            "gust_mph": 6,
            "gust_kph": 9.6,
            "uv": 0.9
          },
          {
            "time_epoch": 1743170400,
            "time": "2025-03-28 15:00",
            "temp_c": 7.3,
            "temp_f": 45.1,
            "is_day": 1,
            "condition": {
              "text": "Llovizna",
              "icon": "//cdn.weatherapi.com/weather/64x64/day/266.png",
              "code": 1153
            },
            "wind_mph": 3.6,
            "wind_kph": 5.8,
            "wind_degree": 329,
            "wind_dir": "NNW",
            "pressure_mb": 1005,
            "pressure_in": 29.67,
            "precip_mm": 0.15,
            "precip_in": 0.01,
            "snow_cm": 0,
            "humidity": 90,
            "cloud": 100,
            "feelslike_c": 6.4,
            "feelslike_f": 43.6,
            "windchill_c": 6.4,
            "windchill_f": 43.6,
            "heatindex_c": 7.3,
            "heatindex_f": 45.1,
            "dewpoint_c": 5.7,
            "dewpoint_f": 42.3,
            "will_it_rain": 1,
            "chance_of_rain": 100,
            "will_it_snow": 0,
            "chance_of_snow": 0,
            "vis_km": 2,
            "vis_miles": 1,
            "gust_mph": 4.8,
            "gust_kph": 7.7,
            "uv": 0.4
          },
          {
            "time_epoch": 1743174000,
            "time": "2025-03-28 16:00",
            "temp_c": 7.1,
            "temp_f": 44.8,
            "is_day": 1,
            "condition": {
              "text": "Llovizna",
              "icon": "//cdn.weatherapi.com/weather/64x64/day/266.png",
              "code": 1153
            },
            "wind_mph": 2.7,
            "wind_kph": 4.3,
            "wind_degree": 342,
            "wind_dir": "NNW",
            "pressure_mb": 1005,
            "pressure_in": 29.67,
            "precip_mm": 0.26,
            "precip_in": 0.01,
            "snow_cm": 0,
            "humidity": 91,
            "cloud": 100,
            "feelslike_c": 6.8,
            "feelslike_f": 44.2,
            "windchill_c": 6.8,
            "windchill_f": 44.2,
            "heatindex_c": 7.1,
            "heatindex_f": 44.8,
            "dewpoint_c": 5.8,
            "dewpoint_f": 42.4,
            "will_it_rain": 1,
            "chance_of_rain": 100,
            "will_it_snow": 0,
            "chance_of_snow": 0,
            "vis_km": 2,
            "vis_miles": 1,
            "gust_mph": 3.6,
            "gust_kph": 5.8,
            "uv": 0.2
          },
          {
            "time_epoch": 1743177600,
            "time": "2025-03-28 17:00",
            "temp_c": 7,
            "temp_f": 44.6,
            "is_day": 1,
            "condition": {
              "text": "Llovizna",
              "icon": "//cdn.weatherapi.com/weather/64x64/day/266.png",
              "code": 1153
            },
            "wind_mph": 2,
            "wind_kph": 3.2,
            "wind_degree": 326,
            "wind_dir": "NNW",
            "pressure_mb": 1005,
            "pressure_in": 29.67,
            "precip_mm": 0.2,
            "precip_in": 0.01,
            "snow_cm": 0,
            "humidity": 92,
            "cloud": 100,
            "feelslike_c": 7.1,
            "feelslike_f": 44.7,
            "windchill_c": 7.1,
            "windchill_f": 44.7,
            "heatindex_c": 7,
            "heatindex_f": 44.6,
            "dewpoint_c": 5.8,
            "dewpoint_f": 42.5,
            "will_it_rain": 1,
            "chance_of_rain": 100,
            "will_it_snow": 0,
            "chance_of_snow": 0,
            "vis_km": 2,
            "vis_miles": 1,
            "gust_mph": 2.8,
            "gust_kph": 4.5,
            "uv": 0.1
          },
          {
            "time_epoch": 1743181200,
            "time": "2025-03-28 18:00",
            "temp_c": 6.8,
            "temp_f": 44.2,
            "is_day": 1,
            "condition": {
              "text": "Lluvia  moderada a intervalos",
              "icon": "//cdn.weatherapi.com/weather/64x64/day/176.png",
              "code": 1063
            },
            "wind_mph": 1.8,
            "wind_kph": 2.9,
            "wind_degree": 287,
            "wind_dir": "WNW",
            "pressure_mb": 1005,
            "pressure_in": 29.68,
            "precip_mm": 0.03,
            "precip_in": 0,
            "snow_cm": 0,
            "humidity": 93,
            "cloud": 87,
            "feelslike_c": 6.8,
            "feelslike_f": 44.2,
            "windchill_c": 6.8,
            "windchill_f": 44.2,
            "heatindex_c": 6.8,
            "heatindex_f": 44.2,
            "dewpoint_c": 5.8,
            "dewpoint_f": 42.4,
            "will_it_rain": 0,
            "chance_of_rain": 56,
            "will_it_snow": 0,
            "chance_of_snow": 0,
            "vis_km": 10,
            "vis_miles": 6,
            "gust_mph": 2.6,
            "gust_kph": 4.2,
            "uv": 0
          },
          {
            "time_epoch": 1743184800,
            "time": "2025-03-28 19:00",
            "temp_c": 6.6,
            "temp_f": 43.9,
            "is_day": 0,
            "condition": {
              "text": "Lluvia  moderada a intervalos",
              "icon": "//cdn.weatherapi.com/weather/64x64/night/176.png",
              "code": 1063
            },
            "wind_mph": 2.2,
            "wind_kph": 3.6,
            "wind_degree": 309,
            "wind_dir": "NW",
            "pressure_mb": 1005,
            "pressure_in": 29.67,
            "precip_mm": 0.08,
            "precip_in": 0,
            "snow_cm": 0,
            "humidity": 93,
            "cloud": 91,
            "feelslike_c": 6.5,
            "feelslike_f": 43.7,
            "windchill_c": 6.5,
            "windchill_f": 43.7,
            "heatindex_c": 6.6,
            "heatindex_f": 44,
            "dewpoint_c": 5.7,
            "dewpoint_f": 42.2,
            "will_it_rain": 1,
            "chance_of_rain": 100,
            "will_it_snow": 0,
            "chance_of_snow": 0,
            "vis_km": 10,
            "vis_miles": 6,
            "gust_mph": 3.4,
            "gust_kph": 5.4,
            "uv": 0
          },
          {
            "time_epoch": 1743188400,
            "time": "2025-03-28 20:00",
            "temp_c": 6.6,
            "temp_f": 43.9,
            "is_day": 0,
            "condition": {
              "text": "Lluvia  moderada a intervalos",
              "icon": "//cdn.weatherapi.com/weather/64x64/night/176.png",
              "code": 1063
            },
            "wind_mph": 1.8,
            "wind_kph": 2.9,
            "wind_degree": 340,
            "wind_dir": "NNW",
            "pressure_mb": 1005,
            "pressure_in": 29.68,
            "precip_mm": 0.13,
            "precip_in": 0.01,
            "snow_cm": 0,
            "humidity": 94,
            "cloud": 100,
            "feelslike_c": 6.6,
            "feelslike_f": 43.8,
            "windchill_c": 6.6,
            "windchill_f": 43.8,
            "heatindex_c": 6.6,
            "heatindex_f": 43.8,
            "dewpoint_c": 5.7,
            "dewpoint_f": 42.2,
            "will_it_rain": 1,
            "chance_of_rain": 100,
            "will_it_snow": 0,
            "chance_of_snow": 0,
            "vis_km": 10,
            "vis_miles": 6,
            "gust_mph": 2.7,
            "gust_kph": 4.3,
            "uv": 0
          },
          {
            "time_epoch": 1743192000,
            "time": "2025-03-28 21:00",
            "temp_c": 6.5,
            "temp_f": 43.7,
            "is_day": 0,
            "condition": {
              "text": "Lluvia  moderada a intervalos",
              "icon": "//cdn.weatherapi.com/weather/64x64/night/176.png",
              "code": 1063
            },
            "wind_mph": 1.3,
            "wind_kph": 2.2,
            "wind_degree": 348,
            "wind_dir": "NNW",
            "pressure_mb": 1005,
            "pressure_in": 29.68,
            "precip_mm": 0.04,
            "precip_in": 0,
            "snow_cm": 0,
            "humidity": 94,
            "cloud": 100,
            "feelslike_c": 6.5,
            "feelslike_f": 43.7,
            "windchill_c": 6.5,
            "windchill_f": 43.7,
            "heatindex_c": 6.5,
            "heatindex_f": 43.7,
            "dewpoint_c": 5.6,
            "dewpoint_f": 42,
            "will_it_rain": 0,
            "chance_of_rain": 68,
            "will_it_snow": 0,
            "chance_of_snow": 0,
            "vis_km": 10,
            "vis_miles": 6,
            "gust_mph": 2,
            "gust_kph": 3.2,
            "uv": 0
          },
          {
            "time_epoch": 1743195600,
            "time": "2025-03-28 22:00",
            "temp_c": 6.4,
            "temp_f": 43.5,
            "is_day": 0,
            "condition": {
              "text": "Neblina",
              "icon": "//cdn.weatherapi.com/weather/64x64/night/143.png",
              "code": 1030
            },
            "wind_mph": 2,
            "wind_kph": 3.2,
            "wind_degree": 5,
            "wind_dir": "N",
            "pressure_mb": 1005,
            "pressure_in": 29.68,
            "precip_mm": 0.06,
            "precip_in": 0,
            "snow_cm": 0,
            "humidity": 94,
            "cloud": 100,
            "feelslike_c": 6.4,
            "feelslike_f": 43.6,
            "windchill_c": 6.4,
            "windchill_f": 43.6,
            "heatindex_c": 6.4,
            "heatindex_f": 43.5,
            "dewpoint_c": 5.6,
            "dewpoint_f": 42,
            "will_it_rain": 1,
            "chance_of_rain": 100,
            "will_it_snow": 0,
            "chance_of_snow": 0,
            "vis_km": 2,
            "vis_miles": 1,
            "gust_mph": 3,
            "gust_kph": 4.8,
            "uv": 0
          },
          {
            "time_epoch": 1743199200,
            "time": "2025-03-28 23:00",
            "temp_c": 6.2,
            "temp_f": 43.2,
            "is_day": 0,
            "condition": {
              "text": "Llovizna",
              "icon": "//cdn.weatherapi.com/weather/64x64/night/266.png",
              "code": 1153
            },
            "wind_mph": 2.5,
            "wind_kph": 4,
            "wind_degree": 6,
            "wind_dir": "N",
            "pressure_mb": 1005,
            "pressure_in": 29.67,
            "precip_mm": 0.21,
            "precip_in": 0.01,
            "snow_cm": 0,
            "humidity": 95,
            "cloud": 100,
            "feelslike_c": 5.9,
            "feelslike_f": 42.7,
            "windchill_c": 5.9,
            "windchill_f": 42.7,
            "heatindex_c": 6.3,
            "heatindex_f": 43.3,
            "dewpoint_c": 5.6,
            "dewpoint_f": 42,
            "will_it_rain": 1,
            "chance_of_rain": 100,
            "will_it_snow": 0,
            "chance_of_snow": 0,
            "vis_km": 2,
            "vis_miles": 1,
            "gust_mph": 3.6,
            "gust_kph": 5.8,
            "uv": 0
          }
        ]
      }
    ]
  }
}
